setup.py
deoga_distributions/Binomialdistribution.py
deoga_distributions/Gaussiandistribution.py
deoga_distributions/Generaldistribution.py
deoga_distributions/__init__.py
deoga_distributions.egg-info/PKG-INFO
deoga_distributions.egg-info/SOURCES.txt
deoga_distributions.egg-info/dependency_links.txt
deoga_distributions.egg-info/not-zip-safe
deoga_distributions.egg-info/top_level.txt