Metadata-Version: 2.1
Name: deoga-distributions
Version: 0.5
Summary: Mathematical distributions
Home-page: UNKNOWN
License: UNKNOWN
Platform: UNKNOWN
